callisto/__init__.py
callisto/__main__.py
callisto/callisto.py
callisto-0.7.dist-info/DESCRIPTION.rst
callisto-0.7.dist-info/METADATA
callisto-0.7.dist-info/RECORD
callisto-0.7.dist-info/WHEEL
callisto-0.7.dist-info/entry_points.txt
callisto-0.7.dist-info/metadata.json
callisto-0.7.dist-info/top_level.txt
