Metadata-Version: 2.0
Name: callisto
Version: 0.7
Summary: Create jupyter kernels from virtual environments
Home-page: https://github.com/ColCarroll/callisto
Author: Colin Carroll
Author-email: colcarroll@gmail.com
License: MIT
Platform: UNKNOWN
Classifier: Development Status :: 3 - Alpha
Classifier: Intended Audience :: Developers
Classifier: License :: OSI Approved :: MIT License
Classifier: Programming Language :: Python :: 2
Classifier: Programming Language :: Python :: 2.7
Classifier: Programming Language :: Python :: 3
Classifier: Programming Language :: Python :: 3.4
Classifier: Programming Language :: Python :: 3.5
Classifier: Programming Language :: Python :: 3.6
Requires-Dist: Click
Requires-Dist: ipykernel
